ispy2_mri/__about__.py
ispy2_mri/__init__.py
ispy2_mri/flowlayout.py
ispy2_mri/ispy2_gui.py
ispy2_mri-0.1.0.dist-info/METADATA
ispy2_mri-0.1.0.dist-info/WHEEL
ispy2_mri-0.1.0.dist-info/entry_points.txt
ispy2_mri-0.1.0.dist-info/licenses/LICENSE.md
ispy2_mri-0.1.0.dist-info/licenses/LICENSE.txt
ispy2_mri-0.1.0.dist-info/RECORD
