Metadata-Version: 2.1
Name: ispy2-mri
Version: 0.1.0
Summary: Log receipt of MRI exams into the database
Project-URL: Documentation, https://github.com/radiology-research/ispy2_mri#readme
Project-URL: Issues, https://github.com/radiology-research/ispy2_mri/issues
Project-URL: Source, https://github.com/radiology-research/ispy2_mri
Author-email: Ross Boylan <ross.boylan@ucsf.edu>
License: # GNU GENERAL PUBLIC LICENSE
License-File: LICENSE.md
License-File: LICENSE.txt
Keywords: GUI,MRI,database,imaging
Classifier: Development Status :: 4 - Beta
Classifier: Environment :: X11 Applications :: Qt
Classifier: Intended Audience :: End Users/Desktop
Classifier: Intended Audience :: Science/Research
Classifier: License :: OSI Approved :: GNU General Public License v3 (GPLv3)
Classifier: Operating System :: Microsoft :: Windows
Classifier: Programming Language :: Python
Classifier: Programming Language :: Python :: 3.10
Classifier: Programming Language :: Python :: 3.11
Classifier: Programming Language :: Python :: Implementation :: CPython
Classifier: Programming Language :: Python :: Implementation :: PyPy
Classifier: Topic :: Database :: Front-Ends
Classifier: Topic :: Scientific/Engineering :: Image Processing
Classifier: Topic :: Software Development :: Code Generators
Requires-Python: >=3.10
Requires-Dist: pyodbc
Requires-Dist: pyside6
